rpi_home/__init__.py
rpi_home/const.py
rpi_home/rpi_home_device.py
rpi_home/rpi_home_driver.py
rpi_home/rpi_home_sampler.py
rpi_home/utils.py
rpi_home/version.py
rpi_home-2.4.4.dist-info/LICENSE
rpi_home-2.4.4.dist-info/METADATA
rpi_home-2.4.4.dist-info/WHEEL
rpi_home-2.4.4.dist-info/top_level.txt
rpi_home-2.4.4.dist-info/RECORD
