Metadata-Version: 2.1
Name: rpi-home
Version: 2.4.4
Summary: python module for rpi-home
Author-email: Bretton Wade <bretton.wade@irdev.us>
Maintainer-email: Bretton Wade <bretton.wade@irdev.us>
License: MIT License
Project-URL: Homepage, https://github.com/brettonw/rpi_home
Keywords: raspberry pi,home assistant
Classifier: Programming Language :: Python
Classifier: Programming Language :: Python :: 3
Requires-Python: >=3.9
License-File: LICENSE
Requires-Dist: toml
Requires-Dist: zeroconf
Requires-Dist: ha-tiny
Provides-Extra: dev
Requires-Dist: pytest; extra == "dev"
